palm_jax/__init__.py
palm_jax/palm.py
palm_jax/palm_lite.py
palm_jax/utils.py
PaLM_jax-0.1.2.dist-info/LICENSE
PaLM_jax-0.1.2.dist-info/METADATA
PaLM_jax-0.1.2.dist-info/WHEEL
PaLM_jax-0.1.2.dist-info/top_level.txt
PaLM_jax-0.1.2.dist-info/RECORD
