Metadata-Version: 2.1
Name: PaLM-jax
Version: 0.1.2
Summary: PaLM: Scaling Language Modeling with Pathways - Jax
Home-page: https://github.com/lucidrains/PaLM-jax
Author: Phil Wang
Author-email: lucidrains@gmail.com
License: MIT
Keywords: artificial intelligence,deep learning,transformers,attention mechanism
Classifier: Development Status :: 4 - Beta
Classifier: Intended Audience :: Developers
Classifier: Topic :: Scientific/Engineering :: Artificial Intelligence
Classifier: License :: OSI Approved :: MIT License
Classifier: Programming Language :: Python :: 3.6
License-File: LICENSE
Requires-Dist: einops (==0.4)
Requires-Dist: equinox (>=0.5)
Requires-Dist: jax (>=0.3.4)
Requires-Dist: jaxlib (>=0.1)
Requires-Dist: optax
Requires-Dist: numpy
